Cargo.toml
MANIFEST.in
README.md
pyproject.toml
setup.py
rastro/__init__.py
rastro.egg-info/PKG-INFO
rastro.egg-info/SOURCES.txt
rastro.egg-info/dependency_links.txt
rastro.egg-info/not-zip-safe
rastro.egg-info/top_level.txt
src/constants.rs
src/lib.rs
src/orbits.rs
test/test_constants.py
test/test_coordinates.py
test/test_orbits.py